backups/__init__.py
backups/apps.py
backups/tests.py
backups/management/commands/__init__.py
backups/management/commands/backupdatabase.py
backups/management/commands/backupmedia.py
django_simple_backups-1.0.dist-info/METADATA
django_simple_backups-1.0.dist-info/WHEEL
django_simple_backups-1.0.dist-info/license
django_simple_backups-1.0.dist-info/top_level.txt
django_simple_backups-1.0.dist-info/RECORD
